doc/__init__.py
docs-code/__init__.py
docs-code/conf.py
dro/__init__.py
dro/src/__init__.py
dro/src/data/__init__.py
dro/src/data/dataloader_classification.py
dro/src/data/dataloader_regression.py
dro/src/data/draw_utils.py
dro/src/data/info.py
dro/src/linear_model/Bayesian_dro.py
dro/src/linear_model/MOT_DRO.py
dro/src/linear_model/OR_Wasserstein_DRO.py
dro/src/linear_model/Wasserstein_DRO.py
dro/src/linear_model/__init__.py
dro/src/linear_model/base.py
dro/src/linear_model/bayesian_dro.py
dro/src/linear_model/chi2_dro.py
dro/src/linear_model/conditional_dro.py
dro/src/linear_model/cvar_dro.py
dro/src/linear_model/hr_dro.py
dro/src/linear_model/kl_dro.py
dro/src/linear_model/marginal_dro.py
dro/src/linear_model/mmd_dro.py
dro/src/linear_model/mot_dro.py
dro/src/linear_model/or_wasserstein_dro.py
dro/src/linear_model/sinkhorn_dro.py
dro/src/linear_model/tv_dro.py
dro/src/linear_model/wasserstein_dro.py
dro/src/neural_model/__init__.py
dro/src/neural_model/base_nn.py
dro/src/neural_model/fdro_nn.py
dro/src/neural_model/fdro_utils.py
dro/src/neural_model/hrdro_nn.py
dro/src/neural_model/wdro_nn.py
dro/src/tree_model/__init__.py
dro/src/tree_model/lgbm.py
dro/src/tree_model/xgb.py
dro-0.3.2.dist-info/licenses/LICENSE
tests/__init__.py
tests/test_bayesian.py
tests/test_conditional.py
tests/test_config.py
tests/test_lgbm.py
tests/test_linear_chi2dro.py
tests/test_linear_cvar.py
tests/test_linear_hrdro.py
tests/test_linear_kldro.py
tests/test_linear_marginal.py
tests/test_linear_mmd.py
tests/test_linear_motdro.py
tests/test_linear_ordro.py
tests/test_linear_sinkhorn.py
tests/test_linear_tvdro.py
tests/test_linear_wdro.py
tests/test_nn_fdro.py
tests/test_nn_hrdro.py
tests/test_nn_wdro.py
tests/test_robust_util.py
tests/test_xgb.py
dro-0.3.2.dist-info/METADATA
dro-0.3.2.dist-info/WHEEL
dro-0.3.2.dist-info/top_level.txt
dro-0.3.2.dist-info/RECORD
