Metadata-Version: 2.4
Name: dro
Version: 0.3.2
Summary: A package of distributionally robust optimization (DRO) methods. Implemented via cvxpy and PyTorch
Home-page: https://github.com/namkoong-lab/dro
Author: DRO developers.
Author-email: liujiashuo77@gmail.com, tw2837@columbia.edu
License: MIT License
Classifier: Programming Language :: Python :: 3
Classifier: License :: OSI Approved :: MIT License
Classifier: Operating System :: MacOS
Classifier: Operating System :: POSIX :: Linux
Requires-Python: >=3.7
License-File: LICENSE
Requires-Dist: pandas
Requires-Dist: numpy>=1.20
Requires-Dist: scikit-learn
Requires-Dist: torch
Requires-Dist: scipy
Requires-Dist: cvxpy
Requires-Dist: torchvision
Requires-Dist: ucimlrepo
Requires-Dist: matplotlib
Requires-Dist: torchattacks
Requires-Dist: mosek>=10.2.17
Requires-Dist: xgboost
Requires-Dist: lightgbm
Dynamic: author
Dynamic: author-email
Dynamic: classifier
Dynamic: description
Dynamic: description-content-type
Dynamic: home-page
Dynamic: license
Dynamic: license-file
Dynamic: requires-dist
Dynamic: requires-python
Dynamic: summary
